stability_toolkit.py
stability_toolkit-1.0.0.dist-info/LICENSE
stability_toolkit-1.0.0.dist-info/METADATA
stability_toolkit-1.0.0.dist-info/WHEEL
stability_toolkit-1.0.0.dist-info/RECORD
