Metadata-Version: 2.3
Name: stability-toolkit
Version: 1.0.0
Summary: A production-ready LangChain toolkit for Stability blockchain interactions without gas fees
License: MIT
Keywords: langchain,blockchain,stability,zkt,web3,ai,agents
Author: Juliun
Author-email: contact@stabilityprotocol.com
Requires-Python: >=3.9,<4.0
Classifier: Development Status :: 5 - Production/Stable
Classifier: Intended Audience :: Developers
Classifier: License :: OSI Approved :: MIT License
Classifier: Programming Language :: Python :: 3
Classifier: Programming Language :: Python :: 3.9
Classifier: Programming Language :: Python :: 3.10
Classifier: Programming Language :: Python :: 3.11
Classifier: Programming Language :: Python :: 3.12
Classifier: Programming Language :: Python :: 3.13
Classifier: Topic :: Internet :: WWW/HTTP
Classifier: Topic :: Scientific/Engineering :: Artificial Intelligence
Classifier: Topic :: Software Development :: Libraries :: Python Modules
Requires-Dist: langchain-core (>=0.1.0,<0.2.0)
Requires-Dist: pydantic (>=1.10.0,<2.0.0)
Requires-Dist: requests (>=2.25.0,<3.0.0)
Project-URL: Bug Tracker, https://github.com/nuljui/stability-toolkit/issues
Project-URL: Documentation, https://github.com/nuljui/stability-toolkit#readme
Project-URL: Homepage, https://github.com/nuljui/stability-toolkit
Project-URL: Portal, https://portal.stabilityprotocol.com/
Project-URL: Repository, https://github.com/nuljui/stability-toolkit
Project-URL: Support, https://github.com/nuljui/stability-toolkit/issues
